mkdocs_plotly_plugin/__init__.py
mkdocs_plotly_plugin/fences.py
mkdocs_plotly_plugin/plugin.py
mkdocs_plotly_plugin/javascripts/mkdocs-plotly-plugin.js
mkdocs_plotly_plugin/templates/ggplot2.json
mkdocs_plotly_plugin/templates/none.json
mkdocs_plotly_plugin/templates/plotly.json
mkdocs_plotly_plugin/templates/plotly_dark.json
mkdocs_plotly_plugin/templates/plotly_dark_min.json
mkdocs_plotly_plugin/templates/plotly_min.json
mkdocs_plotly_plugin/templates/plotly_white.json
mkdocs_plotly_plugin/templates/seaborn.json
mkdocs_plotly_plugin/templates/simple_white.json
mkdocs_plotly_plugin-0.1.2.dist-info/LICENSE
mkdocs_plotly_plugin-0.1.2.dist-info/METADATA
mkdocs_plotly_plugin-0.1.2.dist-info/WHEEL
mkdocs_plotly_plugin-0.1.2.dist-info/entry_points.txt
mkdocs_plotly_plugin-0.1.2.dist-info/top_level.txt
mkdocs_plotly_plugin-0.1.2.dist-info/RECORD
