Metadata-Version: 2.1
Name: mkdocs-plotly-plugin
Version: 0.1.2
Summary: MkDocs plugin to add plotly charts from plotly's json data
Home-page: https://github.com/haoda-li/mkdocs-plotly-plugin
Author: Haoda Li
Author-email: haoda_li@berkeley.edu
License: MIT
Keywords: mkdocs plugin
Classifier: Operating System :: OS Independent
Classifier: Programming Language :: Python
Classifier: Programming Language :: Python :: 3
Classifier: Programming Language :: Python :: 3.7
Classifier: Programming Language :: Python :: 3.8
Classifier: Programming Language :: Python :: 3.9
Classifier: Programming Language :: Python :: 3.10
Classifier: License :: OSI Approved :: MIT License
Requires-Python: >=3.6
License-File: LICENSE
Requires-Dist: mkdocs (>=1.1)
Requires-Dist: pymdown-extensions (>=9.2)
Requires-Dist: beautifulsoup4 (>=4.11.1)
